Workbook

Sheet 🍷 Catálogo de Vinos
A1: 📋 CATÁLOGO DE VINOS — MERCADO LIBRE ARGENTINA
A2: 🔴 Obligatorio (no puede faltar) | H2: 🟡 A completar (recomendado) | O2: 🟢 Calculado automáticamente
A3: IDENTIFICACIÓN | D3: DATOS DEL PRODUCTO | I3: PRECIO Y STOCK | M3: PUBLICACIÓN MELI | Q3: MÉTRICAS
A4: # | B4: Nombre del vino * | C4: Bodega * | D4: Varietal * | E4: Año cosecha | F4: Región / Valle | G4: Volumen (ml) * | H4: GTIN / EAN (cód. barras)* | I4: Precio lista (ARS) * | J4: Precio oferta (ARS) | K4: % Descuento | L4: Stock actual * | M4: Tipo publicación * | N4: Envío gratis | O4: ID publicación MeLi | P4: Estado publicación | Q4: Visitas (sem) | R4: Ventas totales | S4: Preguntas pendientes | T4: Score calidad /10
A5: 17 | B5: Reserva Las Perdices Chardonnay | C5: Viña las Perdices | D5: Chardonnay | E5: 2020 | F5: Lujan de Cuyo | G5: 750 | H5: 7798123970685 | I5: 12500 | K5: =IF(AND(I5>0,J5>0),1-J5/I5,"") | L5: 3
A6: 18 | B6: Reserva Las Perdices Bonarda | C6: Viña las Perdices | D6: Bonarda | E6: 2018 | F6: Lujan de Cuyo | G6: 750 | H6: 7798123970265 | I6: 11500 | K6: =IF(AND(I6>0,J6>0),1-J6/I6,"") | L6: 1
A7: 26 | K7: =IF(AND(I7>0,J7>0),1-J7/I7,"")
A8: 27 | K8: =IF(AND(I8>0,J8>0),1-J8/I8,"")
A9: 28 | K9: =IF(AND(I9>0,J9>0),1-J9/I9,"")
A10: 29 | K10: =IF(AND(I10>0,J10>0),1-J10/I10,"")
A11: 30 | K11: =IF(AND(I11>0,J11>0),1-J11/I11,"")
A12: 31 | K12: =IF(AND(I12>0,J12>0),1-J12/I12,"")
A13: 32 | K13: =IF(AND(I13>0,J13>0),1-J13/I13,"")
A14: 33 | K14: =IF(AND(I14>0,J14>0),1-J14/I14,"")
A15: 34 | K15: =IF(AND(I15>0,J15>0),1-J15/I15,"")
A16: 35 | K16: =IF(AND(I16>0,J16>0),1-J16/I16,"")
A17: 36 | K17: =IF(AND(I17>0,J17>0),1-J17/I17,"")
A18: 37 | K18: =IF(AND(I18>0,J18>0),1-J18/I18,"")
... A31: 50 | K31: =IF(AND(I31>0,J31>0),1-J31/I31,"")

Sheet 📸 Fotos y Contenido
A1: 📸 CONTROL DE FOTOS Y CONTENIDO POR PUBLICACIÓN
A2: ✅ = Listo | ⏳ = En proceso | ❌ = Pendiente — Completá una celda por foto
A4: Nombre del vino | B4: Foto frontal (fondo blanco) | C4: Contraetiqueta | D4: Detalle corcho | E4: Botella completa | F4: Copa servida | G4: Pack / Combo | H4: Título MeLi optimizado | I4: Descripción 200+ palabras | J4: Keywords agregadas | K4: GTIN cargado
A5: =IF('🍷 Catálogo de Vinos'!#REF!<>"", '🍷 Catálogo de Vinos'!#REF!, "") -> #REF! | H5: Cabernet Sauvignon Altocedro Año Cero 2020 Valle de Uco 750ml Vino Tinto Premium | I5: Cabernet Sauvignon Altocedro Año Cero 2020, Valle de Uco, Mendoza. Botella 750ml. Elaborado por Bodega Altocedro en uno de los valles más prestigiosos de Argentina, este vino tinto premium expresa con fidelidad el terroir de altura del Valle de Uco. Color rojo rubí profundo con destellos violáceos. En nariz presenta aromas intensos de frutos negros maduros como cassis y ciruela, acompañados de notas especiadas, pimiento rojo y un elegante toque mineral. En boca es estructurado, con taninos firmes pero sedosos, buena acidez y un final largo y persistente. Fermentación en depósitos de acero inoxidable con posterior crianza en madera. Temperatura de servicio ideal entre 16 y 18 grados. Maridaje perfecto con cortes de carne vacuna, asado argentino, pastas con salsas intensas, quesos estacionados y embutidos. Un vino de alta gama ideal para coleccionistas y amantes del vino fino argentino. Perfecto como regalo premium o para ocasiones especiales. Vino tinto reserva Mendoza, Cabernet Sauvignon premium Argentina, vino fino Valle de Uco
A6: =IF('🍷 Catálogo de Vinos'!#REF!<>"", '🍷 Catálogo de Vinos'!#REF!, "") -> #REF! | H6: Red Blend Renacer Milamore 2019 Lujan de Cuyo 750ml Vino Tinto Alta Gama | I6: Red Blend Renacer Milamore 2019, Luján de Cuyo, Mendoza. Botella 750ml. Bodega Renacer presenta Milamore, un blend de tintos de autor elaborado en Luján de Cuyo, subregión emblemática de Mendoza reconocida mundialmente por la calidad de sus vinos. Color rojo granate intenso con bordes violáceos. Nariz compleja y seductora con frutos rojos y negros maduros, notas de especias dulces, vainilla, chocolate amargo y suaves toques de roble. En boca es voluminoso, con taninos pulidos y una acidez equilibrada que otorga frescura y elegancia. Final prolongado con reminiscencias frutales y especiadas. Crianza parcial en barricas de roble francés y americano. Temperatura de servicio recomendada entre 16 y 18 grados. Ideal para maridar con asado de tira, costillas de cordero, pasta con ragú, quesos duros y tabla de fiambres gourmet. Un vino de alta expresión, ideal como regalo corporativo o para celebraciones especiales. Vino tinto blend premium Mendoza, Red Blend alta gama Argentina, vino fino Luján de Cuyo.
A7: =IF('🍷 Catálogo de Vinos'!#REF!<>"", '🍷 Catálogo de Vinos'!#REF!, "") -> #REF!
A8: =IF('🍷 Catálogo de Vinos'!#REF!<>"", '🍷 Catálogo de Vinos'!#REF!, "") -> #REF!
A9: =IF('🍷 Catálogo de Vinos'!#REF!<>"", '🍷 Catálogo de Vinos'!#REF!, "") -> #REF!
A10: =IF('🍷 Catálogo de Vinos'!#REF!<>"", '🍷 Catálogo de Vinos'!#REF!, "") -> #REF!
A11: =IF('🍷 Catálogo de Vinos'!#REF!<>"", '🍷 Catálogo de Vinos'!#REF!, "") -> #REF!
A12: =IF('🍷 Catálogo de Vinos'!#REF!<>"", '🍷 Catálogo de Vinos'!#REF!, "") -> #REF!
A13: =IF('🍷 Catálogo de Vinos'!#REF!<>"", '🍷 Catálogo de Vinos'!#REF!, "") -> #REF!
A14: =IF('🍷 Catálogo de Vinos'!#REF!<>"", '🍷 Catálogo de Vinos'!#REF!, "") -> #REF!
A15: =IF('🍷 Catálogo de Vinos'!#REF!<>"", '🍷 Catálogo de Vinos'!#REF!, "") -> #REF!
A16: =IF('🍷 Catálogo de Vinos'!#REF!<>"", '🍷 Catálogo de Vinos'!#REF!, "") -> #REF!
A17: =IF('🍷 Catálogo de Vinos'!#REF!<>"", '🍷 Catálogo de Vinos'!#REF!, "") -> #REF!
A18: =IF('🍷 Catálogo de Vinos'!#REF!<>"", '🍷 Catálogo de Vinos'!#REF!, "") -> #REF!
... A20: =IF('🍷 Catálogo de Vinos'!#REF!<>"", '🍷 Catálogo de Vinos'!#REF!, "") -> #REF!
A21: =IF('🍷 Catálogo de Vinos'!B5<>"", '🍷 Catálogo de Vinos'!B5, "") -> Reserva Las Perdices Chardonnay
A22: =IF('🍷 Catálogo de Vinos'!B6<>"", '🍷 Catálogo de Vinos'!B6, "") -> Reserva Las Perdices Bonarda
A23: =IF('🍷 Catálogo de Vinos'!#REF!<>"", '🍷 Catálogo de Vinos'!#REF!, "") -> #REF!
A24: =IF('🍷 Catálogo de Vinos'!#REF!<>"", '🍷 Catálogo de Vinos'!#REF!, "") -> #REF!
A25: =IF('🍷 Catálogo de Vinos'!#REF!<>"", '🍷 Catálogo de Vinos'!#REF!, "") -> #REF!
A26: =IF('🍷 Catálogo de Vinos'!#REF!<>"", '🍷 Catálogo de Vinos'!#REF!, "") -> #REF!
A27: =IF('🍷 Catálogo de Vinos'!#REF!<>"", '🍷 Catálogo de Vinos'!#REF!, "") -> #REF!
A28: =IF('🍷 Catálogo de Vinos'!#REF!<>"", '🍷 Catálogo de Vinos'!#REF!, "") -> #REF!
A29: =IF('🍷 Catálogo de Vinos'!#REF!<>"", '🍷 Catálogo de Vinos'!#REF!, "") -> #REF!
A30: =IF('🍷 Catálogo de Vinos'!B7<>"", '🍷 Catálogo de Vinos'!B7, "")
A31: =IF('🍷 Catálogo de Vinos'!B8<>"", '🍷 Catálogo de Vinos'!B8, "")
A32: =IF('🍷 Catálogo de Vinos'!B9<>"", '🍷 Catálogo de Vinos'!B9, "")
A33: =IF('🍷 Catálogo de Vinos'!B10<>"", '🍷 Catálogo de Vinos'!B10, "")
A34: =IF('🍷 Catálogo de Vinos'!B11<>"", '🍷 Catálogo de Vinos'!B11, "")
A35: =IF('🍷 Catálogo de Vinos'!B12<>"", '🍷 Catálogo de Vinos'!B12, "")
A36: =IF('🍷 Catálogo de Vinos'!B13<>"", '🍷 Catálogo de Vinos'!B13, "")
A37: =IF('🍷 Catálogo de Vinos'!B14<>"", '🍷 Catálogo de Vinos'!B14, "")
A38: =IF('🍷 Catálogo de Vinos'!B15<>"", '🍷 Catálogo de Vinos'!B15, "")
A39: =IF('🍷 Catálogo de Vinos'!B16<>"", '🍷 Catálogo de Vinos'!B16, "")
A40: =IF('🍷 Catálogo de Vinos'!B17<>"", '🍷 Catálogo de Vinos'!B17, "")
A41: =IF('🍷 Catálogo de Vinos'!B18<>"", '🍷 Catálogo de Vinos'!B18, "")
... A54: =IF('🍷 Catálogo de Vinos'!B31<>"", '🍷 Catálogo de Vinos'!B31, "")

Sheet 📊 Seguimiento Ventas
A1: 📊 SEGUIMIENTO DIARIO DE VENTAS — META: 1 VENTA/DÍA
A2: Completá Fecha, Producto vendido, Cantidad y Precio. El resto se calcula solo.
A4: Fecha * | B4: Producto vendido * | C4: Cantidad * | D4: Precio unitario * | E4: Total venta | F4: Comisión MeLi | G4: Neto recibido | H4: Costo envío | I4: Ganancia neta | J4: Notas / Canal
E5: =IF(AND(C5>0,D5>0),C5*D5,"") | F5: =IF(E5<>"",E5*0.13,"") | G5: =IF(E5<>"",E5-F5,"") | I5: =IF(G5<>"",G5-IF(H5<>"",H5,0),"")
E6: =IF(AND(C6>0,D6>0),C6*D6,"") | F6: =IF(E6<>"",E6*0.13,"") | G6: =IF(E6<>"",E6-F6,"") | I6: =IF(G6<>"",G6-IF(H6<>"",H6,0),"")
E7: =IF(AND(C7>0,D7>0),C7*D7,"") | F7: =IF(E7<>"",E7*0.13,"") | G7: =IF(E7<>"",E7-F7,"") | I7: =IF(G7<>"",G7-IF(H7<>"",H7,0),"")
E8: =IF(AND(C8>0,D8>0),C8*D8,"") | F8: =IF(E8<>"",E8*0.13,"") | G8: =IF(E8<>"",E8-F8,"") | I8: =IF(G8<>"",G8-IF(H8<>"",H8,0),"")
E9: =IF(AND(C9>0,D9>0),C9*D9,"") | F9: =IF(E9<>"",E9*0.13,"") | G9: =IF(E9<>"",E9-F9,"") | I9: =IF(G9<>"",G9-IF(H9<>"",H9,0),"")
E10: =IF(AND(C10>0,D10>0),C10*D10,"") | F10: =IF(E10<>"",E10*0.13,"") | G10: =IF(E10<>"",E10-F10,"") | I10: =IF(G10<>"",G10-IF(H10<>"",H10,0),"")
E11: =IF(AND(C11>0,D11>0),C11*D11,"") | F11: =IF(E11<>"",E11*0.13,"") | G11: =IF(E11<>"",E11-F11,"") | I11: =IF(G11<>"",G11-IF(H11<>"",H11,0),"")
E12: =IF(AND(C12>0,D12>0),C12*D12,"") | F12: =IF(E12<>"",E12*0.13,"") | G12: =IF(E12<>"",E12-F12,"") | I12: =IF(G12<>"",G12-IF(H12<>"",H12,0),"")
E13: =IF(AND(C13>0,D13>0),C13*D13,"") | F13: =IF(E13<>"",E13*0.13,"") | G13: =IF(E13<>"",E13-F13,"") | I13: =IF(G13<>"",G13-IF(H13<>"",H13,0),"")
E14: =IF(AND(C14>0,D14>0),C14*D14,"") | F14: =IF(E14<>"",E14*0.13,"") | G14: =IF(E14<>"",E14-F14,"") | I14: =IF(G14<>"",G14-IF(H14<>"",H14,0),"")
E15: =IF(AND(C15>0,D15>0),C15*D15,"") | F15: =IF(E15<>"",E15*0.13,"") | G15: =IF(E15<>"",E15-F15,"") | I15: =IF(G15<>"",G15-IF(H15<>"",H15,0),"")
E16: =IF(AND(C16>0,D16>0),C16*D16,"") | F16: =IF(E16<>"",E16*0.13,"") | G16: =IF(E16<>"",E16-F16,"") | I16: =IF(G16<>"",G16-IF(H16<>"",H16,0),"")
... E64: =IF(AND(C64>0,D64>0),C64*D64,"") | F64: =IF(E64<>"",E64*0.13,"") | G64: =IF(E64<>"",E64-F64,"") | I64: =IF(G64<>"",G64-IF(H64<>"",H64,0),"")
A65: TOTALES | C65: =SUM(C5:C64) -> 0 | E65: =SUM(E5:E64) -> 0 | F65: =SUM(F5:F64) -> 0 | G65: =SUM(G5:G64) -> 0 | H65: =SUM(H5:H64) -> 0 | I65: =SUM(I5:I64) -> 0

Sheet ℹ️ Instrucciones
A1: ℹ️ GUÍA DE USO — CÓMO COMPLETAR ESTE ARCHIVO
B3: PASO 1 | C3: Empezar por acá → Hoja: 🍷 Catálogo de Vinos
C4: Completá una fila por cada vino.
C5: Las celdas ROJAS son obligatorias para que la API de MeLi pueda crear la publicación.
C6: Las celdas AMARILLAS son recomendadas para mejorar el score de calidad.
C7: Las celdas VERDES se calculan solas, no las toques.
B9: PASO 2 | C9: Controlar fotos → Hoja: 📸 Fotos y Contenido
C10: Los nombres de los vinos se copian automáticamente del Catálogo.
C11: Para cada vino, marcá el estado de cada foto: ✅ Listo / ⏳ En proceso / ❌ Pendiente.
C12: Necesitás mínimo 6 fotos por publicación para el score máximo.
B14: PASO 3 | C14: Registrar ventas → Hoja: 📊 Seguimiento Ventas
C15: Cada vez que vendas, agregá una fila con Fecha, Producto, Cantidad y Precio.
C16: Total, comisión MeLi (13% Gold), neto y ganancia se calculan solos.
C17: Meta diaria: 1 venta. Revisá los totales abajo para ver tu progreso.
B19: GTIN / EAN | C19: ¿Dónde lo encuentro?
C20: Es el código de barras impreso en la contraetiqueta de cada botella.
C21: Buscalo con tu celular en la app de cámara o en una app de scanner.
C22: Sin GTIN el score de calidad de MeLi baja significativamente.
B24: TIPO PUB. | C24: Diferencia clave
C25: Gratuita: 0% comisión, casi sin visibilidad. No usar.
C26: Clásica: ~8% comisión, visibilidad media.
C27: Gold: ~13% comisión, alta visibilidad. Recomendado.
C28: Gold Premium: ~16% comisión, máxima visibilidad. Para alta gama.
B30: API MELI | C30: Para carga masiva
C31: Cuando tengas este Excel completo, el script Python lo lee y sube todo automáticamente.
C32: Necesitás: APP_ID + SECRET de developers.mercadolibre.com.ar + fotos en carpetas.
